{
  "generated_at_utc": "2026-06-24T13:42:11.591503+00:00",
  "sensors": [
    {
      "sensor_index": 83971,
      "last_seen": 1782308448,
      "last_seen_iso_utc": "2026-06-24T13:40:48+00:00",
      "humidity": 68,
      "pm25_atm": 13.3,
      "pm25_atm_a": 11.8,
      "pm25_atm_b": 14.8,
      "pm25_best": 13.3,
      "pm25_corr": 8.807947019867552,
      "pm_method": "avg",
      "is_fresh": true,
      "name": "WCAS_Entwistle2(AQSU-858E)",
      "latitude": 53.59378,
      "longitude": -114.9758,
      "geometry": null
    },
    {
      "sensor_index": 91545,
      "last_seen": 1782308447,
      "last_seen_iso_utc": "2026-06-24T13:40:47+00:00",
      "humidity": 100,
      "pm25_atm": 6.5,
      "pm25_atm_a": 6.4,
      "pm25_atm_b": 6.5,
      "pm25_best": 6.5,
      "pm25_corr": 4.166666666666667,
      "pm_method": "avg",
      "is_fresh": true,
      "name": "WCAS_Entwistle1(AQSU-6463)",
      "latitude": 53.593525,
      "longitude": -114.971245,
      "geometry": null
    },
    {
      "sensor_index": 166965,
      "last_seen": 1782308488,
      "last_seen_iso_utc": "2026-06-24T13:41:28+00:00",
      "humidity": 53,
      "pm25_atm": 7.6,
      "pm25_atm_a": 7.7,
      "pm25_atm_b": 7.5,
      "pm25_best": 7.6,
      "pm25_corr": 5.981245813797722,
      "pm_method": "avg",
      "is_fresh": true,
      "name": "WCAS_Evansburg1 (AQSU-A26A)",
      "latitude": 53.60466,
      "longitude": -115.018326,
      "geometry": null
    },
    {
      "sensor_index": 249949,
      "last_seen": 1782308407,
      "last_seen_iso_utc": "2026-06-24T13:40:07+00:00",
      "humidity": 53,
      "pm25_atm": 7.2,
      "pm25_atm_a": 6.8,
      "pm25_atm_b": 7.5,
      "pm25_best": 7.2,
      "pm25_corr": 5.666443402545211,
      "pm_method": "avg",
      "is_fresh": true,
      "name": "WCAS_EntwistleRecCentre",
      "latitude": 53.593185,
      "longitude": -114.99485,
      "geometry": null
    }
  ],
  "light": {
    "lifx_device_id": "D073D5D54604",
    "strategy": "average_fresh_sensors",
    "used_sensor_indices": [
      83971,
      91545,
      166965,
      249949
    ],
    "used_pm25_corr": 6.155575725719288,
    "color_hex": "#01cbff",
    "duration_sec": 60
  }
}