{
  "generated_at_utc": "2026-04-04T08:11:15.586653+00:00",
  "sensors": [
    {
      "sensor_index": 83971,
      "last_seen": 1775290219,
      "last_seen_iso_utc": "2026-04-04T08:10:19+00:00",
      "humidity": 69,
      "pm25_atm": 14.2,
      "pm25_atm_a": 11.7,
      "pm25_atm_b": 16.7,
      "pm25_best": 14.2,
      "pm25_corr": 9.255677039529015,
      "pm_method": "avg",
      "is_fresh": true,
      "name": "WCAS_Entwistle2(AQSU-858E)",
      "latitude": 53.59378,
      "longitude": -114.9758,
      "geometry": "POINT (-114.9758 53.59378)"
    },
    {
      "sensor_index": 91545,
      "last_seen": 1775290214,
      "last_seen_iso_utc": "2026-04-04T08:10:14+00:00",
      "humidity": 65,
      "pm25_atm": 18.2,
      "pm25_atm_a": 18.6,
      "pm25_atm_b": 17.9,
      "pm25_best": 18.2,
      "pm25_corr": 12.58893280632411,
      "pm_method": "avg",
      "is_fresh": true,
      "name": "WCAS_Entwistle1(AQSU-6463)",
      "latitude": 53.593525,
      "longitude": -114.971245,
      "geometry": "POINT (-114.971245 53.593525)"
    },
    {
      "sensor_index": 166965,
      "last_seen": 1775290224,
      "last_seen_iso_utc": "2026-04-04T08:10:24+00:00",
      "humidity": 70,
      "pm25_atm": 17.0,
      "pm25_atm_a": 14.2,
      "pm25_atm_b": 19.7,
      "pm25_best": 17.0,
      "pm25_corr": 10.897435897435898,
      "pm_method": "avg",
      "is_fresh": true,
      "name": "WCAS_Evansburg1 (AQSU-A26A)",
      "latitude": 53.60466,
      "longitude": -115.018326,
      "geometry": "POINT (-115.018326 53.60466)"
    },
    {
      "sensor_index": 249949,
      "last_seen": 1775290179,
      "last_seen_iso_utc": "2026-04-04T08:09:39+00:00",
      "humidity": 75,
      "pm25_atm": 24.5,
      "pm25_atm_a": 24.1,
      "pm25_atm_b": 24.9,
      "pm25_best": 24.5,
      "pm25_corr": 15.705128205128204,
      "pm_method": "avg",
      "is_fresh": true,
      "name": "WCAS_EntwistleRecCentre",
      "latitude": 53.593185,
      "longitude": -114.99485,
      "geometry": "POINT (-114.99485 53.593185)"
    }
  ],
  "light": {
    "lifx_device_id": "D073D5D54604",
    "strategy": "average_fresh_sensors",
    "used_sensor_indices": [
      83971,
      91545,
      166965,
      249949
    ],
    "used_pm25_corr": 12.111793487104308,
    "color_hex": "#0099cb",
    "duration_sec": 60
  }
}